README.rst
setup.py
rsession/__init__.py
rsession/rsession.py
rsession.egg-info/PKG-INFO
rsession.egg-info/SOURCES.txt
rsession.egg-info/dependency_links.txt
rsession.egg-info/not-zip-safe
rsession.egg-info/top_level.txt