Metadata-Version: 1.1
Name: rsession
Version: 0.1.0
Summary: Django session back-end persisting to Redis
Home-page: https://github.com/aquamatt/rsession/
Author: Matthew Pontefract
Author-email: matthew@zorinholdings.com
License: BSD
Keywords: django,sessions,redis
Platform: UNKNOWN
Classifier: Environment :: Web Environment
Classifier: Intended Audience :: Developers
Classifier: License :: OSI Approved :: BSD License
Classifier: Operating System :: OS Independent
Classifier: Programming Language :: Python
Classifier: Framework :: Django
